[{"line":20,"elements":[{"start_timestamp":"2024-07-07T05:03:27.322Z","line":23,"name":"Navigate to Flipkart and verify categories, validate carousel, and compare products","description":"","id":"flipkart-automation;navigate-to-flipkart-and-verify-categories--validate-carousel--and-compare-products","type":"scenario","keyword":"Scenario","steps":[{"result":{"duration":2115295600,"status":"passed"},"line":24,"name":"I navigate to Flipkart","match":{"location":"testDefinition.flipkart.i_navigate_to_flipkart()"},"keyword":"Given "},{"result":{"duration":1325483700,"status":"passed"},"line":25,"name":"I fetch all categories visible below the search bar and verify the text","match":{"location":"testDefinition.flipkart.i_fetch_all_categories_visible_below_the_search_bar_and_verify_the_text()"},"keyword":"Then "},{"result":{"duration":2580724900,"status":"passed"},"line":26,"name":"I validate the carousel showing offers","match":{"location":"testDefinition.flipkart.i_validate_the_carousel_showing_offers()"},"keyword":"And "},{"result":{"duration":185692500,"status":"passed"},"line":27,"name":"I select a product and search for it","match":{"location":"testDefinition.flipkart.i_select_a_product_and_search_for_it()"},"keyword":"When "},{"result":{"duration":5613534100,"status":"passed"},"line":28,"name":"I open the details page of the product","match":{"location":"testDefinition.flipkart.i_open_the_details_page_of_the_product()"},"keyword":"Then "},{"result":{"duration":7457515700,"status":"passed"},"line":29,"name":"I check the compare checkbox and validate if the compare modal opens","match":{"location":"testDefinition.flipkart.i_check_the_compare_checkbox_and_validate_if_the_compare_modal_opens()"},"keyword":"And "},{"result":{"duration":7515994900,"status":"passed"},"line":30,"name":"I click on the compare modal","match":{"location":"testDefinition.flipkart.i_click_on_the_compare_modal()"},"keyword":"When "},{"result":{"duration":1290800,"status":"passed"},"line":31,"name":"I validate the selected device is visible on the compare page","match":{"location":"testDefinition.flipkart.i_validate_the_selected_device_is_visible_on_the_compare_page()"},"keyword":"Then "},{"result":{"duration":21375682600,"status":"passed"},"line":32,"name":"I add three more products to the compare page making a total of four products","match":{"location":"testDefinition.flipkart.i_add_three_more_products_to_the_compare_page_making_a_total_of_four_products()"},"keyword":"And "},{"result":{"status":"passed"},"line":33,"name":"I fetch ratings and reviews for all four products","match":{"location":"testDefinition.flipkart.i_fetch_ratings_and_reviews_for_all_four_products()"},"keyword":"Then "}],"tags":[{"name":"@tag"},{"name":"@tag1"}]}],"name":"Flipkart Automation","description":"","id":"flipkart-automation","keyword":"Feature","uri":"file:src/test/resources/Flipkart/Assignment.feature","tags":[{"name":"@tag","type":"Tag","location":{"line":19,"column":1}}]}]